{
    "Name": "Denmark",
    "Capital": "Copenhagen",
    "States": {
        "Hovedstaden": {
            "Code": "84"
        },
        "Midtjylland": {
            "Code": "82"
        },
        "Nordjylland": {
            "Code": "81"
        },
        "Sjælland": {
            "Code": "85"
        },
        "Syddanmark": {
            "Code": "83"
        }
    },
    "ShortCodes": {
        "Code1": "DK",
        "Code2": "DNK"
    },
    "Region": "Europe",
    "Sub Region": "Northern Europe",
    "Currency": {
        "Code": "DKK",
        "Name": "Danish krone",
        "Symbol": "kr"
    },
    "Languages": {
        "Code": "da",
        "Native Name": "Danish"
    },
    "Dialing Code": "+45",
    "Population": 0,
    "Area": 0,
    "Borders": [],
    "Timezones": [],
    "Flag": "https://restcountries.eu/data/dnk.svg"
}