{
    "Name": "Cocos (Keeling) Islands",
    "Capital": "West Island",
    "States": {},
    "ShortCodes": {
        "Code1": "CC",
        "Code2": "CCK"
    },
    "Region": "Oceania",
    "Sub Region": "Australia and New Zealand",
    "Currency": {
        "Code": "",
        "Name": "",
        "Symbol": ""
    },
    "Languages": {
        "Code": "",
        "Native Name": "",
        "Name": "",
        "ISO": ""
    },
    "Dialing Code": "+61",
    "Population": 0,
    "Area": 0,
    "Borders": [],
    "Timezones": [],
    "Flag": ""
}