{
    "Name": "Fiji",
    "Capital": "Suva",
    "States": {
        "Central": {
            "Code": "C"
        },
        "Eastern": {
            "Code": "E"
        },
        "Northern": {
            "Code": "N"
        },
        "Rotuma": {
            "Code": "R"
        },
        "Western": {
            "Code": "W"
        }
    },
    "ShortCodes": {
        "Code1": "FJ",
        "Code2": "FJI"
    },
    "Region": "Oceania",
    "Sub Region": "Melanesia",
    "Currency": {
        "Code": "FJD",
        "Name": "Fijian dollar",
        "Symbol": "$"
    },
    "Languages": {
        "Code": "en",
        "Native Name": "English"
    },
    "Dialing Code": "+679",
    "Population": 0,
    "Area": 0,
    "Borders": [],
    "Timezones": [],
    "Flag": "https://restcountries.eu/data/fji.svg"
}